{
  "protocol_version" : "0.0.6",
  "configuration" : {
    "version" : "(6.13.0) (explicit/1f1b5a84)",
    "tlc" : "__thread",
    "sigsgev" : "normal",
    "notifications" : "kqueue",
    "architecture" : "arm64",
    "disabled_features" : "com,shared_perfcounters",
    "smallconfig" : "disabled",
    "bigarrays" : "disabled",
    "softdebug" : "enabled",
    "interpreter" : "enabled",
    "llvm_support" : "disabled",
    "suspend" : "preemptive"
  },
  "memory" : {
    "Resident Size" : "543424512",
    "Virtual Size" : "424023506944",
    "minor_gc_time" : "0",
    "major_gc_time" : "2448066",
    "minor_gc_count" : "0",
    "major_gc_count" : "19",
    "major_gc_time_concurrent" : "0"
 },
  "threads" : [
 {
    "is_managed" : false,
    "offset_free_hash" : "0x0",
    "offset_rich_hash" : "0x0",
    "crashed" : false,
    "native_thread_id" : "0x34f787000",
    "thread_info_addr" : "0x34b0abc00",
    "thread_name" : "tid_2ad2f",
    "ctx" : {
      "IP" : "0x18711e170",
      "SP" : "0x34f786d50",
      "BP" : "0x34f786d60"
  },
    "unmanaged_frames" : [
  {
      "is_managed" : "false",
      "native_address" : "0x31f0c519c",
      "native_offset" : "0x00000"
   }
,
  {
      "is_managed" : "false",
      "native_address" : "0x31f1fc518",
      "native_offset" : "0x00000"
   }
,
  {
      "is_managed" : "false",
      "native_address" : "0x31f1fc874",
      "native_offset" : "0x00000"
   }
,
  {
      "is_managed" : "false",
      "native_address" : "0x31f1fc63c",
      "native_offset" : "0x00000"
   }
,
  {
      "is_managed" : "false",
      "native_address" : "0x31f1063cc",
      "native_offset" : "0x00000"
   }
,
  {
      "is_managed" : "false",
      "native_address" : "0x18718f584",
      "native_offset" : "0x00000"
   }
,
  {
      "is_managed" : "false",
      "native_address" : "0x186fae984",
      "native_offset" : "0x00000"
   }
,
  {
      "is_managed" : "false",
      "native_address" : "0x186faf034",
      "native_offset" : "0x00000"
   }
,
  {
      "is_managed" : "false",
      "native_address" : "0x1059b4164",
      "native_offset" : "0x00000"
   }
,
  {
      "is_managed" : "false",
      "native_address" : "0x103368098",
      "native_offset" : "0x00000"
   }
,
  {
      "is_managed" : "false",
      "native_address" : "0x10376e078",
      "native_offset" : "0x00000"
   }
,
  {
      "is_managed" : "false",
      "native_address" : "0x10376e014",
      "native_offset" : "0x00000"
   }
,
  {
      "is_managed" : "false",
      "native_address" : "0x10392287c",
      "native_offset" : "0x00000"
   }
,
  {
      "is_managed" : "false",
      "native_address" : "0x18715ef94",
      "native_offset" : "0x00000"
   }
,
  {
      "is_managed" : "false",
      "native_address" : "0x187159d34",
      "native_offset" : "0x00000"
   }

  ]
 },
 {
    "is_managed" : false,
    "offset_free_hash" : "0x0",
    "offset_rich_hash" : "0x0",
    "crashed" : false,
    "native_thread_id" : "0x31fafb000",
    "thread_info_addr" : "0x124b99400",
    "thread_name" : "Debugger agent",
    "ctx" : {
      "IP" : "0x187126b44",
      "SP" : "0x31fafaaa0",
      "BP" : "0x31fafaae0"
  },
    "unmanaged_frames" : [
  {
      "is_managed" : "false",
      "native_address" : "0x31f0c519c",
      "native_offset" : "0x00000"
   }
,
  {
      "is_managed" : "false",
      "native_address" : "0x31f1fc518",
      "native_offset" : "0x00000"
   }
,
  {
      "is_managed" : "false",
      "native_address" : "0x31f1fc874",
      "native_offset" : "0x00000"
   }
,
  {
      "is_managed" : "false",
      "native_address" : "0x31f1fc63c",
      "native_offset" : "0x00000"
   }
,
  {
      "is_managed" : "false",
      "native_address" : "0x31f1063cc",
      "native_offset" : "0x00000"
   }
,
  {
      "is_managed" : "false",
      "native_address" : "0x18718f584",
      "native_offset" : "0x00000"
   }
,
  {
      "is_managed" : "false",
      "native_address" : "0x31f135598",
      "native_offset" : "0x00000"
   }
,
  {
      "is_managed" : "false",
      "native_address" : "0x31f12c194",
      "native_offset" : "0x00000"
   }
,
  {
      "is_managed" : "false",
      "native_address" : "0x31f1fd284",
      "native_offset" : "0x00000"
   }
,
  {
      "is_managed" : "false",
      "native_address" : "0x31f1fd130",
      "native_offset" : "0x00000"
   }
,
  {
      "is_managed" : "false",
      "native_address" : "0x31f27ccf8",
      "native_offset" : "0x00000"
   }
,
  {
      "is_managed" : "false",
      "native_address" : "0x31f27cc80",
      "native_offset" : "0x00000"
   }
,
  {
      "is_managed" : "false",
      "native_address" : "0x18715ef94",
      "native_offset" : "0x00000"
   }
,
  {
      "is_managed" : "false",
      "native_address" : "0x187159d34",
      "native_offset" : "0x00000"
   }

  ]
 },
 {
    "is_managed" : false,
    "offset_free_hash" : "0x0",
    "offset_rich_hash" : "0x0",
    "crashed" : true,
    "native_thread_id" : "0x1eef98c00",
    "thread_info_addr" : "0x124124800",
    "thread_name" : "tid_103",
    "ctx" : {
      "IP" : "0x103aa3144",
      "SP" : "0x16d039050",
      "BP" : "0x16d0390c0"
  },
    "unmanaged_frames" : [
  {
      "is_managed" : "false",
      "native_address" : "0x31f0c519c",
      "native_offset" : "0x00000"
   }
,
  {
      "is_managed" : "false",
      "native_address" : "0x31f1fc518",
      "native_offset" : "0x00000"
   }
,
  {
      "is_managed" : "false",
      "native_address" : "0x31f1fc874",
      "native_offset" : "0x00000"
   }
,
  {
      "is_managed" : "false",
      "native_address" : "0x31f1fce64",
      "native_offset" : "0x00000"
   }
,
  {
      "is_managed" : "false",
      "native_address" : "0x31f107218",
      "native_offset" : "0x00000"
   }
,
  {
      "is_managed" : "false",
      "native_address" : "0x31f0c9334",
      "native_offset" : "0x00000"
   }
,
  {
      "is_managed" : "false",
      "native_address" : "0x31f051ac4",
      "native_offset" : "0x00000"
   }
,
  {
      "is_managed" : "false",
      "native_address" : "0x18718f584",
      "native_offset" : "0x00000"
   }
,
  {
      "is_managed" : "false",
      "native_address" : "0x103aa3140",
      "native_offset" : "0x00000"
   }
,
  {
      "is_managed" : "false",
      "native_address" : "0x103a8defc",
      "native_offset" : "0x00000"
   }
,
  {
      "is_managed" : "false",
      "native_address" : "0x103bdaa48",
      "native_offset" : "0x00000"
   }
,
  {
      "is_managed" : "false",
      "native_address" : "0x103bbb8c8",
      "native_offset" : "0x00000"
   }
,
  {
      "is_managed" : "false",
      "native_address" : "0x103bc745c",
      "native_offset" : "0x00000"
   }
,
  {
      "is_managed" : "false",
      "native_address" : "0x103ba8a24",
      "native_offset" : "0x00000"
   }
,
  {
      "is_managed" : "false",
      "native_address" : "0x103ba8f5c",
      "native_offset" : "0x00000"
   }
,
  {
      "is_managed" : "false",
      "native_address" : "0x103ba9168",
      "native_offset" : "0x00000"
   }
,
  {
      "is_managed" : "false",
      "native_address" : "0x104f22ec0",
      "native_offset" : "0x00000"
   }
,
  {
      "is_managed" : "false",
      "native_address" : "0x104f22c70",
      "native_offset" : "0x00000"
   }
,
  {
      "is_managed" : "false",
      "native_address" : "0x104f22fbc",
      "native_offset" : "0x00000"
   }
,
  {
      "is_managed" : "false",
      "native_address" : "0x104e729b8",
      "native_offset" : "0x00000"
   }
,
  {
      "is_managed" : "false",
      "native_address" : "0x104e96568",
      "native_offset" : "0x00000"
   }
,
  {
      "is_managed" : "false",
      "native_address" : "0x104e75140",
      "native_offset" : "0x00000"
   }
,
  {
      "is_managed" : "false",
      "native_address" : "0x104e77218",
      "native_offset" : "0x00000"
   }
,
  {
      "is_managed" : "false",
      "native_address" : "0x104de90ec",
      "native_offset" : "0x00000"
   }
,
  {
      "is_managed" : "false",
      "native_address" : "0x1046931ac",
      "native_offset" : "0x00000"
   }
,
  {
      "is_managed" : "false",
      "native_address" : "0x1058f0490",
      "native_offset" : "0x00000"
   }
,
  {
      "is_managed" : "false",
      "native_address" : "0x187233144",
      "native_offset" : "0x00000"
   }
,
  {
      "is_managed" : "false",
      "native_address" : "0x1872c73d8",
      "native_offset" : "0x00000"
   }
,
  {
      "is_managed" : "false",
      "native_address" : "0x1872c7320",
      "native_offset" : "0x00000"
   }
,
  {
      "is_managed" : "false",
      "native_address" : "0x187201678",
      "native_offset" : "0x00000"
   }
,
  {
      "is_managed" : "false",
      "native_address" : "0x18831e4e4",
      "native_offset" : "0x00000"
   }
,
  {
      "is_managed" : "false",
      "native_address" : "0x18abed9a4",
      "native_offset" : "0x00000"
   }
,
  {
      "is_managed" : "false",
      "native_address" : "0x18b2908d8",
      "native_offset" : "0x00000"
   }
,
  {
      "is_managed" : "false",
      "native_address" : "0x1059098b0",
      "native_offset" : "0x00000"
   }
,
  {
      "is_managed" : "false",
      "native_address" : "0x1058f13e8",
      "native_offset" : "0x00000"
   }
,
  {
      "is_managed" : "false",
      "native_address" : "0x1883aa4a8",
      "native_offset" : "0x00000"
   }
,
  {
      "is_managed" : "false",
      "native_address" : "0x18725a5b8",
      "native_offset" : "0x00000"
   }
,
  {
      "is_managed" : "false",
      "native_address" : "0x18725a25c",
      "native_offset" : "0x00000"
   }
,
  {
      "is_managed" : "false",
      "native_address" : "0x187259d94",
      "native_offset" : "0x00000"
   }
,
  {
      "is_managed" : "false",
      "native_address" : "0x18723d1cc",
      "native_offset" : "0x00000"
   }
,
  {
      "is_managed" : "false",
      "native_address" : "0x18723c434",
      "native_offset" : "0x00000"
   }
,
  {
      "is_managed" : "false",
      "native_address" : "0x1919e019c",
      "native_offset" : "0x00000"
   }
,
  {
      "is_managed" : "false",
      "native_address" : "0x1919dffd8",
      "native_offset" : "0x00000"
   }
,
  {
      "is_managed" : "false",
      "native_address" : "0x1919dfd30",
      "native_offset" : "0x00000"
   }
,
  {
      "is_managed" : "false",
      "native_address" : "0x18aa9bd68",
      "native_offset" : "0x00000"
   }
,
  {
      "is_managed" : "false",
      "native_address" : "0x18b291808",
      "native_offset" : "0x00000"
   }
,
  {
      "is_managed" : "false",
      "native_address" : "0x1058f1244",
      "native_offset" : "0x00000"
   }
,
  {
      "is_managed" : "false",
      "native_address" : "0x1883aa4a8",
      "native_offset" : "0x00000"
   }
,
  {
      "is_managed" : "false",
      "native_address" : "0x18725a5b8",
      "native_offset" : "0x00000"
   }
,
  {
      "is_managed" : "false",
      "native_address" : "0x18725a25c",
      "native_offset" : "0x00000"
   }
,
  {
      "is_managed" : "false",
      "native_address" : "0x187259d94",
      "native_offset" : "0x00000"
   }
,
  {
      "is_managed" : "false",
      "native_address" : "0x18723d1cc",
      "native_offset" : "0x00000"
   }
,
  {
      "is_managed" : "false",
      "native_address" : "0x18723c434",
      "native_offset" : "0x00000"
   }
,
  {
      "is_managed" : "false",
      "native_address" : "0x1919e019c",
      "native_offset" : "0x00000"
   }
,
  {
      "is_managed" : "false",
      "native_address" : "0x1919dffd8",
      "native_offset" : "0x00000"
   }
,
  {
      "is_managed" : "false",
      "native_address" : "0x1919dfd30",
      "native_offset" : "0x00000"
   }
,
  {
      "is_managed" : "false",
      "native_address" : "0x18aa9bd68",
      "native_offset" : "0x00000"
   }
,
  {
      "is_managed" : "false",
      "native_address" : "0x18b291808",
      "native_offset" : "0x00000"
   }
,
  {
      "is_managed" : "false",
      "native_address" : "0x18aa8f09c",
      "native_offset" : "0x00000"
   }
,
  {
      "is_managed" : "false",
      "native_address" : "0x18aa662e0",
      "native_offset" : "0x00000"
   }
,
  {
      "is_managed" : "false",
      "native_address" : "0x10590a184",
      "native_offset" : "0x00000"
   }
,
  {
      "is_managed" : "false",
      "native_address" : "0x10590a4e8",
      "native_offset" : "0x00000"
   }
,
  {
      "is_managed" : "false",
      "native_address" : "0x186dd60e0",
      "native_offset" : "0x00000"
   }

  ]
 },
 {
    "is_managed" : false,
    "offset_free_hash" : "0x0",
    "offset_rich_hash" : "0x0",
    "crashed" : false,
    "native_thread_id" : "0x356dc7000",
    "thread_info_addr" : "0x325bf7a00",
    "thread_name" : "Thread Pool Worker",
    "ctx" : {
      "IP" : "0x18711e188",
      "SP" : "0x356dc6db0",
      "BP" : "0x356dc6e50"
  },
    "unmanaged_frames" : [
  {
      "is_managed" : "false",
      "native_address" : "0x31f0c519c",
      "native_offset" : "0x00000"
   }
,
  {
      "is_managed" : "false",
      "native_address" : "0x31f1fc518",
      "native_offset" : "0x00000"
   }
,
  {
      "is_managed" : "false",
      "native_address" : "0x31f1fc874",
      "native_offset" : "0x00000"
   }
,
  {
      "is_managed" : "false",
      "native_address" : "0x31f1fc63c",
      "native_offset" : "0x00000"
   }
,
  {
      "is_managed" : "false",
      "native_address" : "0x31f1063cc",
      "native_offset" : "0x00000"
   }
,
  {
      "is_managed" : "false",
      "native_address" : "0x18718f584",
      "native_offset" : "0x00000"
   }
,
  {
      "is_managed" : "false",
      "native_address" : "0x31f1551c0",
      "native_offset" : "0x00000"
   }
,
  {
      "is_managed" : "false",
      "native_address" : "0x31f1fd284",
      "native_offset" : "0x00000"
   }
,
  {
      "is_managed" : "false",
      "native_address" : "0x31f1fd130",
      "native_offset" : "0x00000"
   }
,
  {
      "is_managed" : "false",
      "native_address" : "0x31f27ccf8",
      "native_offset" : "0x00000"
   }
,
  {
      "is_managed" : "false",
      "native_address" : "0x31f27cc80",
      "native_offset" : "0x00000"
   }
,
  {
      "is_managed" : "false",
      "native_address" : "0x18715ef94",
      "native_offset" : "0x00000"
   }
,
  {
      "is_managed" : "false",
      "native_address" : "0x187159d34",
      "native_offset" : "0x00000"
   }

  ]
 },
 {
    "is_managed" : false,
    "offset_free_hash" : "0x0",
    "offset_rich_hash" : "0x0",
    "crashed" : false,
    "native_thread_id" : "0x370e03000",
    "thread_info_addr" : "0x34ae58000",
    "thread_name" : "Thread Pool Worker",
    "ctx" : {
      "IP" : "0x18711e188",
      "SP" : "0x370e02db0",
      "BP" : "0x370e02e50"
  },
    "unmanaged_frames" : [
  {
      "is_managed" : "false",
      "native_address" : "0x31f0c519c",
      "native_offset" : "0x00000"
   }
,
  {
      "is_managed" : "false",
      "native_address" : "0x31f1fc518",
      "native_offset" : "0x00000"
   }
,
  {
      "is_managed" : "false",
      "native_address" : "0x31f1fc874",
      "native_offset" : "0x00000"
   }
,
  {
      "is_managed" : "false",
      "native_address" : "0x31f1fc63c",
      "native_offset" : "0x00000"
   }
,
  {
      "is_managed" : "false",
      "native_address" : "0x31f1063cc",
      "native_offset" : "0x00000"
   }
,
  {
      "is_managed" : "false",
      "native_address" : "0x18718f584",
      "native_offset" : "0x00000"
   }
,
  {
      "is_managed" : "false",
      "native_address" : "0x31f1551c0",
      "native_offset" : "0x00000"
   }
,
  {
      "is_managed" : "false",
      "native_address" : "0x31f1fd284",
      "native_offset" : "0x00000"
   }
,
  {
      "is_managed" : "false",
      "native_address" : "0x31f1fd130",
      "native_offset" : "0x00000"
   }
,
  {
      "is_managed" : "false",
      "native_address" : "0x31f27ccf8",
      "native_offset" : "0x00000"
   }
,
  {
      "is_managed" : "false",
      "native_address" : "0x31f27cc80",
      "native_offset" : "0x00000"
   }
,
  {
      "is_managed" : "false",
      "native_address" : "0x18715ef94",
      "native_offset" : "0x00000"
   }
,
  {
      "is_managed" : "false",
      "native_address" : "0x187159d34",
      "native_offset" : "0x00000"
   }

  ]
 },
 {
    "is_managed" : false,
    "offset_free_hash" : "0x0",
    "offset_rich_hash" : "0x0",
    "crashed" : false,
    "native_thread_id" : "0x36021b000",
    "thread_info_addr" : "0x125d45000",
    "thread_name" : "Thread Pool Worker",
    "ctx" : {
      "IP" : "0x18711e188",
      "SP" : "0x36021adb0",
      "BP" : "0x36021ae50"
  },
    "unmanaged_frames" : [
  {
      "is_managed" : "false",
      "native_address" : "0x31f0c519c",
      "native_offset" : "0x00000"
   }
,
  {
      "is_managed" : "false",
      "native_address" : "0x31f1fc518",
      "native_offset" : "0x00000"
   }
,
  {
      "is_managed" : "false",
      "native_address" : "0x31f1fc874",
      "native_offset" : "0x00000"
   }
,
  {
      "is_managed" : "false",
      "native_address" : "0x31f1fc63c",
      "native_offset" : "0x00000"
   }
,
  {
      "is_managed" : "false",
      "native_address" : "0x31f1063cc",
      "native_offset" : "0x00000"
   }
,
  {
      "is_managed" : "false",
      "native_address" : "0x18718f584",
      "native_offset" : "0x00000"
   }
,
  {
      "is_managed" : "false",
      "native_address" : "0x31f1551c0",
      "native_offset" : "0x00000"
   }
,
  {
      "is_managed" : "false",
      "native_address" : "0x31f1fd284",
      "native_offset" : "0x00000"
   }
,
  {
      "is_managed" : "false",
      "native_address" : "0x31f1fd130",
      "native_offset" : "0x00000"
   }
,
  {
      "is_managed" : "false",
      "native_address" : "0x31f27ccf8",
      "native_offset" : "0x00000"
   }
,
  {
      "is_managed" : "false",
      "native_address" : "0x31f27cc80",
      "native_offset" : "0x00000"
   }
,
  {
      "is_managed" : "false",
      "native_address" : "0x18715ef94",
      "native_offset" : "0x00000"
   }
,
  {
      "is_managed" : "false",
      "native_address" : "0x187159d34",
      "native_offset" : "0x00000"
   }

  ]
 },
 {
    "is_managed" : false,
    "offset_free_hash" : "0x0",
    "offset_rich_hash" : "0x0",
    "crashed" : false,
    "native_thread_id" : "0x364043000",
    "thread_info_addr" : "0x325de2400",
    "thread_name" : "Thread Pool Worker",
    "ctx" : {
      "IP" : "0x18711e188",
      "SP" : "0x364042db0",
      "BP" : "0x364042e50"
  },
    "unmanaged_frames" : [
  {
      "is_managed" : "false",
      "native_address" : "0x31f0c519c",
      "native_offset" : "0x00000"
   }
,
  {
      "is_managed" : "false",
      "native_address" : "0x31f1fc518",
      "native_offset" : "0x00000"
   }
,
  {
      "is_managed" : "false",
      "native_address" : "0x31f1fc874",
      "native_offset" : "0x00000"
   }
,
  {
      "is_managed" : "false",
      "native_address" : "0x31f1fc63c",
      "native_offset" : "0x00000"
   }
,
  {
      "is_managed" : "false",
      "native_address" : "0x31f1063cc",
      "native_offset" : "0x00000"
   }
,
  {
      "is_managed" : "false",
      "native_address" : "0x18718f584",
      "native_offset" : "0x00000"
   }
,
  {
      "is_managed" : "false",
      "native_address" : "0x31f1551c0",
      "native_offset" : "0x00000"
   }
,
  {
      "is_managed" : "false",
      "native_address" : "0x31f1fd284",
      "native_offset" : "0x00000"
   }
,
  {
      "is_managed" : "false",
      "native_address" : "0x31f1fd130",
      "native_offset" : "0x00000"
   }
,
  {
      "is_managed" : "false",
      "native_address" : "0x31f27ccf8",
      "native_offset" : "0x00000"
   }
,
  {
      "is_managed" : "false",
      "native_address" : "0x31f27cc80",
      "native_offset" : "0x00000"
   }
,
  {
      "is_managed" : "false",
      "native_address" : "0x18715ef94",
      "native_offset" : "0x00000"
   }
,
  {
      "is_managed" : "false",
      "native_address" : "0x187159d34",
      "native_offset" : "0x00000"
   }

  ]
 },
 {
    "is_managed" : false,
    "offset_free_hash" : "0x0",
    "offset_rich_hash" : "0x0",
    "crashed" : false,
    "native_thread_id" : "0x360633000",
    "thread_info_addr" : "0x125e44000",
    "thread_name" : "Thread Pool Worker",
    "ctx" : {
      "IP" : "0x18711e188",
      "SP" : "0x360632db0",
      "BP" : "0x360632e50"
  },
    "unmanaged_frames" : [
  {
      "is_managed" : "false",
      "native_address" : "0x31f0c519c",
      "native_offset" : "0x00000"
   }
,
  {
      "is_managed" : "false",
      "native_address" : "0x31f1fc518",
      "native_offset" : "0x00000"
   }
,
  {
      "is_managed" : "false",
      "native_address" : "0x31f1fc874",
      "native_offset" : "0x00000"
   }
,
  {
      "is_managed" : "false",
      "native_address" : "0x31f1fc63c",
      "native_offset" : "0x00000"
   }
,
  {
      "is_managed" : "false",
      "native_address" : "0x31f1063cc",
      "native_offset" : "0x00000"
   }
,
  {
      "is_managed" : "false",
      "native_address" : "0x18718f584",
      "native_offset" : "0x00000"
   }
,
  {
      "is_managed" : "false",
      "native_address" : "0x31f1551c0",
      "native_offset" : "0x00000"
   }
,
  {
      "is_managed" : "false",
      "native_address" : "0x31f1fd284",
      "native_offset" : "0x00000"
   }
,
  {
      "is_managed" : "false",
      "native_address" : "0x31f1fd130",
      "native_offset" : "0x00000"
   }
,
  {
      "is_managed" : "false",
      "native_address" : "0x31f27ccf8",
      "native_offset" : "0x00000"
   }
,
  {
      "is_managed" : "false",
      "native_address" : "0x31f27cc80",
      "native_offset" : "0x00000"
   }
,
  {
      "is_managed" : "false",
      "native_address" : "0x18715ef94",
      "native_offset" : "0x00000"
   }
,
  {
      "is_managed" : "false",
      "native_address" : "0x187159d34",
      "native_offset" : "0x00000"
   }

  ]
 },
 {
    "is_managed" : false,
    "offset_free_hash" : "0x0",
    "offset_rich_hash" : "0x0",
    "crashed" : false,
    "native_thread_id" : "0x36681b000",
    "thread_info_addr" : "0x324940c00",
    "thread_name" : "Thread Pool Worker",
    "ctx" : {
      "IP" : "0x18711e188",
      "SP" : "0x36681adb0",
      "BP" : "0x36681ae50"
  },
    "unmanaged_frames" : [
  {
      "is_managed" : "false",
      "native_address" : "0x31f0c519c",
      "native_offset" : "0x00000"
   }
,
  {
      "is_managed" : "false",
      "native_address" : "0x31f1fc518",
      "native_offset" : "0x00000"
   }
,
  {
      "is_managed" : "false",
      "native_address" : "0x31f1fc874",
      "native_offset" : "0x00000"
   }
,
  {
      "is_managed" : "false",
      "native_address" : "0x31f1fc63c",
      "native_offset" : "0x00000"
   }
,
  {
      "is_managed" : "false",
      "native_address" : "0x31f1063cc",
      "native_offset" : "0x00000"
   }
,
  {
      "is_managed" : "false",
      "native_address" : "0x18718f584",
      "native_offset" : "0x00000"
   }
,
  {
      "is_managed" : "false",
      "native_address" : "0x31f1551c0",
      "native_offset" : "0x00000"
   }
,
  {
      "is_managed" : "false",
      "native_address" : "0x31f1fd284",
      "native_offset" : "0x00000"
   }
,
  {
      "is_managed" : "false",
      "native_address" : "0x31f1fd130",
      "native_offset" : "0x00000"
   }
,
  {
      "is_managed" : "false",
      "native_address" : "0x31f27ccf8",
      "native_offset" : "0x00000"
   }
,
  {
      "is_managed" : "false",
      "native_address" : "0x31f27cc80",
      "native_offset" : "0x00000"
   }
,
  {
      "is_managed" : "false",
      "native_address" : "0x18715ef94",
      "native_offset" : "0x00000"
   }
,
  {
      "is_managed" : "false",
      "native_address" : "0x187159d34",
      "native_offset" : "0x00000"
   }

  ]
 },
 {
    "is_managed" : false,
    "offset_free_hash" : "0x0",
    "offset_rich_hash" : "0x0",
    "crashed" : false,
    "native_thread_id" : "0x35f297000",
    "thread_info_addr" : "0x126814200",
    "thread_name" : "Thread Pool Worker",
    "ctx" : {
      "IP" : "0x18711e188",
      "SP" : "0x35f296db0",
      "BP" : "0x35f296e50"
  },
    "unmanaged_frames" : [
  {
      "is_managed" : "false",
      "native_address" : "0x31f0c519c",
      "native_offset" : "0x00000"
   }
,
  {
      "is_managed" : "false",
      "native_address" : "0x31f1fc518",
      "native_offset" : "0x00000"
   }
,
  {
      "is_managed" : "false",
      "native_address" : "0x31f1fc874",
      "native_offset" : "0x00000"
   }
,
  {
      "is_managed" : "false",
      "native_address" : "0x31f1fc63c",
      "native_offset" : "0x00000"
   }
,
  {
      "is_managed" : "false",
      "native_address" : "0x31f1063cc",
      "native_offset" : "0x00000"
   }
,
  {
      "is_managed" : "false",
      "native_address" : "0x18718f584",
      "native_offset" : "0x00000"
   }
,
  {
      "is_managed" : "false",
      "native_address" : "0x31f1551c0",
      "native_offset" : "0x00000"
   }
,
  {
      "is_managed" : "false",
      "native_address" : "0x31f1fd284",
      "native_offset" : "0x00000"
   }
,
  {
      "is_managed" : "false",
      "native_address" : "0x31f1fd130",
      "native_offset" : "0x00000"
   }
,
  {
      "is_managed" : "false",
      "native_address" : "0x31f27ccf8",
      "native_offset" : "0x00000"
   }
,
  {
      "is_managed" : "false",
      "native_address" : "0x31f27cc80",
      "native_offset" : "0x00000"
   }
,
  {
      "is_managed" : "false",
      "native_address" : "0x18715ef94",
      "native_offset" : "0x00000"
   }
,
  {
      "is_managed" : "false",
      "native_address" : "0x187159d34",
      "native_offset" : "0x00000"
   }

  ]
 },
 {
    "is_managed" : false,
    "offset_free_hash" : "0x0",
    "offset_rich_hash" : "0x0",
    "crashed" : false,
    "native_thread_id" : "0x32a207000",
    "thread_info_addr" : "0x125ad7800",
    "thread_name" : "Thread Pool I/O Selector",
    "ctx" : {
      "IP" : "0x187129358",
      "SP" : "0x32a206ae0",
      "BP" : "0x32a206ce0"
  },
    "unmanaged_frames" : [
  {
      "is_managed" : "false",
      "native_address" : "0x31f0c519c",
      "native_offset" : "0x00000"
   }
,
  {
      "is_managed" : "false",
      "native_address" : "0x31f1fc518",
      "native_offset" : "0x00000"
   }
,
  {
      "is_managed" : "false",
      "native_address" : "0x31f1fc874",
      "native_offset" : "0x00000"
   }
,
  {
      "is_managed" : "false",
      "native_address" : "0x31f1fc63c",
      "native_offset" : "0x00000"
   }
,
  {
      "is_managed" : "false",
      "native_address" : "0x31f1063cc",
      "native_offset" : "0x00000"
   }
,
  {
      "is_managed" : "false",
      "native_address" : "0x18718f584",
      "native_offset" : "0x00000"
   }
,
  {
      "is_managed" : "false",
      "native_address" : "0x31f24e810",
      "native_offset" : "0x00000"
   }
,
  {
      "is_managed" : "false",
      "native_address" : "0x31f201a54",
      "native_offset" : "0x00000"
   }
,
  {
      "is_managed" : "false",
      "native_address" : "0x31f20146c",
      "native_offset" : "0x00000"
   }
,
  {
      "is_managed" : "false",
      "native_address" : "0x31f1fd284",
      "native_offset" : "0x00000"
   }
,
  {
      "is_managed" : "false",
      "native_address" : "0x31f1fd130",
      "native_offset" : "0x00000"
   }
,
  {
      "is_managed" : "false",
      "native_address" : "0x31f27ccf8",
      "native_offset" : "0x00000"
   }
,
  {
      "is_managed" : "false",
      "native_address" : "0x31f27cc80",
      "native_offset" : "0x00000"
   }
,
  {
      "is_managed" : "false",
      "native_address" : "0x18715ef94",
      "native_offset" : "0x00000"
   }
,
  {
      "is_managed" : "false",
      "native_address" : "0x187159d34",
      "native_offset" : "0x00000"
   }

  ]
 },
 {
    "is_managed" : false,
    "offset_free_hash" : "0x0",
    "offset_rich_hash" : "0x0",
    "crashed" : false,
    "native_thread_id" : "0x31f8ef000",
    "thread_info_addr" : "0x124b96200",
    "thread_name" : "Finalizer",
    "ctx" : {
      "IP" : "0x18711e170",
      "SP" : "0x31f8eedd0",
      "BP" : "0x31f8eee50"
  },
    "unmanaged_frames" : [
  {
      "is_managed" : "false",
      "native_address" : "0x31f0c519c",
      "native_offset" : "0x00000"
   }
,
  {
      "is_managed" : "false",
      "native_address" : "0x31f1fc518",
      "native_offset" : "0x00000"
   }
,
  {
      "is_managed" : "false",
      "native_address" : "0x31f1fc874",
      "native_offset" : "0x00000"
   }
,
  {
      "is_managed" : "false",
      "native_address" : "0x31f1fc63c",
      "native_offset" : "0x00000"
   }
,
  {
      "is_managed" : "false",
      "native_address" : "0x31f1063cc",
      "native_offset" : "0x00000"
   }
,
  {
      "is_managed" : "false",
      "native_address" : "0x18718f584",
      "native_offset" : "0x00000"
   }
,
  {
      "is_managed" : "false",
      "native_address" : "0x31f23616c",
      "native_offset" : "0x00000"
   }
,
  {
      "is_managed" : "false",
      "native_address" : "0x31f1fd284",
      "native_offset" : "0x00000"
   }
,
  {
      "is_managed" : "false",
      "native_address" : "0x31f1fd130",
      "native_offset" : "0x00000"
   }
,
  {
      "is_managed" : "false",
      "native_address" : "0x31f27ccf8",
      "native_offset" : "0x00000"
   }
,
  {
      "is_managed" : "false",
      "native_address" : "0x31f27cc80",
      "native_offset" : "0x00000"
   }
,
  {
      "is_managed" : "false",
      "native_address" : "0x18715ef94",
      "native_offset" : "0x00000"
   }
,
  {
      "is_managed" : "false",
      "native_address" : "0x187159d34",
      "native_offset" : "0x00000"
   }

  ]
 },
 {
    "is_managed" : false,
    "offset_free_hash" : "0x0",
    "offset_rich_hash" : "0x0",
    "crashed" : false,
    "native_thread_id" : "0x356bbb000",
    "thread_info_addr" : "0x3518d1800",
    "thread_name" : "tid_2d807",
    "ctx" : {
      "IP" : "0x1871219ec",
      "SP" : "0x356bbac20",
      "BP" : "0x356bbacb0"
  },
    "unmanaged_frames" : [
  {
      "is_managed" : "false",
      "native_address" : "0x31f0c519c",
      "native_offset" : "0x00000"
   }
,
  {
      "is_managed" : "false",
      "native_address" : "0x31f1fc518",
      "native_offset" : "0x00000"
   }
,
  {
      "is_managed" : "false",
      "native_address" : "0x31f1fc874",
      "native_offset" : "0x00000"
   }
,
  {
      "is_managed" : "false",
      "native_address" : "0x31f1fc63c",
      "native_offset" : "0x00000"
   }
,
  {
      "is_managed" : "false",
      "native_address" : "0x31f1063cc",
      "native_offset" : "0x00000"
   }
,
  {
      "is_managed" : "false",
      "native_address" : "0x18718f584",
      "native_offset" : "0x00000"
   }
,
  {
      "is_managed" : "false",
      "native_address" : "0x18715f588",
      "native_offset" : "0x00000"
   }
,
  {
      "is_managed" : "false",
      "native_address" : "0x31f24bd6c",
      "native_offset" : "0x00000"
   }
,
  {
      "is_managed" : "false",
      "native_address" : "0x31f255a48",
      "native_offset" : "0x00000"
   }
,
  {
      "is_managed" : "false",
      "native_address" : "0x31f1549c8",
      "native_offset" : "0x00000"
   }
,
  {
      "is_managed" : "false",
      "native_address" : "0x31f1fd284",
      "native_offset" : "0x00000"
   }
,
  {
      "is_managed" : "false",
      "native_address" : "0x31f1fd130",
      "native_offset" : "0x00000"
   }
,
  {
      "is_managed" : "false",
      "native_address" : "0x31f27ccf8",
      "native_offset" : "0x00000"
   }
,
  {
      "is_managed" : "false",
      "native_address" : "0x31f27cc80",
      "native_offset" : "0x00000"
   }
,
  {
      "is_managed" : "false",
      "native_address" : "0x18715ef94",
      "native_offset" : "0x00000"
   }
,
  {
      "is_managed" : "false",
      "native_address" : "0x187159d34",
      "native_offset" : "0x00000"
   }

  ]
 },
 {
    "is_managed" : false,
    "offset_free_hash" : "0x0",
    "offset_rich_hash" : "0x0",
    "crashed" : false,
    "native_thread_id" : "0x366c07000",
    "thread_info_addr" : "0x352feb600",
    "thread_name" : "Thread Pool Worker",
    "ctx" : {
      "IP" : "0x18711e188",
      "SP" : "0x366c06db0",
      "BP" : "0x366c06e50"
  },
    "unmanaged_frames" : [
  {
      "is_managed" : "false",
      "native_address" : "0x31f0c519c",
      "native_offset" : "0x00000"
   }
,
  {
      "is_managed" : "false",
      "native_address" : "0x31f1fc518",
      "native_offset" : "0x00000"
   }
,
  {
      "is_managed" : "false",
      "native_address" : "0x31f1fc874",
      "native_offset" : "0x00000"
   }
,
  {
      "is_managed" : "false",
      "native_address" : "0x31f1fc63c",
      "native_offset" : "0x00000"
   }
,
  {
      "is_managed" : "false",
      "native_address" : "0x31f1063cc",
      "native_offset" : "0x00000"
   }
,
  {
      "is_managed" : "false",
      "native_address" : "0x18718f584",
      "native_offset" : "0x00000"
   }
,
  {
      "is_managed" : "false",
      "native_address" : "0x31f1551c0",
      "native_offset" : "0x00000"
   }
,
  {
      "is_managed" : "false",
      "native_address" : "0x31f1fd284",
      "native_offset" : "0x00000"
   }
,
  {
      "is_managed" : "false",
      "native_address" : "0x31f1fd130",
      "native_offset" : "0x00000"
   }
,
  {
      "is_managed" : "false",
      "native_address" : "0x31f27ccf8",
      "native_offset" : "0x00000"
   }
,
  {
      "is_managed" : "false",
      "native_address" : "0x31f27cc80",
      "native_offset" : "0x00000"
   }
,
  {
      "is_managed" : "false",
      "native_address" : "0x18715ef94",
      "native_offset" : "0x00000"
   }
,
  {
      "is_managed" : "false",
      "native_address" : "0x187159d34",
      "native_offset" : "0x00000"
   }

  ]
 },
 {
    "is_managed" : false,
    "offset_free_hash" : "0x0",
    "offset_rich_hash" : "0x0",
    "crashed" : false,
    "native_thread_id" : "0x363e37000",
    "thread_info_addr" : "0x34ab0ce00",
    "thread_name" : "Thread Pool Worker",
    "ctx" : {
      "IP" : "0x18711e188",
      "SP" : "0x363e36db0",
      "BP" : "0x363e36e50"
  },
    "unmanaged_frames" : [
  {
      "is_managed" : "false",
      "native_address" : "0x31f0c519c",
      "native_offset" : "0x00000"
   }
,
  {
      "is_managed" : "false",
      "native_address" : "0x31f1fc518",
      "native_offset" : "0x00000"
   }
,
  {
      "is_managed" : "false",
      "native_address" : "0x31f1fc874",
      "native_offset" : "0x00000"
   }
,
  {
      "is_managed" : "false",
      "native_address" : "0x31f1fc63c",
      "native_offset" : "0x00000"
   }
,
  {
      "is_managed" : "false",
      "native_address" : "0x31f1063cc",
      "native_offset" : "0x00000"
   }
,
  {
      "is_managed" : "false",
      "native_address" : "0x18718f584",
      "native_offset" : "0x00000"
   }
,
  {
      "is_managed" : "false",
      "native_address" : "0x31f1551c0",
      "native_offset" : "0x00000"
   }
,
  {
      "is_managed" : "false",
      "native_address" : "0x31f1fd284",
      "native_offset" : "0x00000"
   }
,
  {
      "is_managed" : "false",
      "native_address" : "0x31f1fd130",
      "native_offset" : "0x00000"
   }
,
  {
      "is_managed" : "false",
      "native_address" : "0x31f27ccf8",
      "native_offset" : "0x00000"
   }
,
  {
      "is_managed" : "false",
      "native_address" : "0x31f27cc80",
      "native_offset" : "0x00000"
   }
,
  {
      "is_managed" : "false",
      "native_address" : "0x18715ef94",
      "native_offset" : "0x00000"
   }
,
  {
      "is_managed" : "false",
      "native_address" : "0x187159d34",
      "native_offset" : "0x00000"
   }

  ]
 },
 {
    "is_managed" : false,
    "offset_free_hash" : "0x0",
    "offset_rich_hash" : "0x0",
    "crashed" : false,
    "native_thread_id" : "0x360427000",
    "thread_info_addr" : "0x351d63400",
    "thread_name" : "Thread Pool Worker",
    "ctx" : {
      "IP" : "0x18711e188",
      "SP" : "0x360426db0",
      "BP" : "0x360426e50"
  },
    "unmanaged_frames" : [
  {
      "is_managed" : "false",
      "native_address" : "0x31f0c519c",
      "native_offset" : "0x00000"
   }
,
  {
      "is_managed" : "false",
      "native_address" : "0x31f1fc518",
      "native_offset" : "0x00000"
   }
,
  {
      "is_managed" : "false",
      "native_address" : "0x31f1fc874",
      "native_offset" : "0x00000"
   }
,
  {
      "is_managed" : "false",
      "native_address" : "0x31f1fc63c",
      "native_offset" : "0x00000"
   }
,
  {
      "is_managed" : "false",
      "native_address" : "0x31f1063cc",
      "native_offset" : "0x00000"
   }
,
  {
      "is_managed" : "false",
      "native_address" : "0x18718f584",
      "native_offset" : "0x00000"
   }
,
  {
      "is_managed" : "false",
      "native_address" : "0x31f1551c0",
      "native_offset" : "0x00000"
   }
,
  {
      "is_managed" : "false",
      "native_address" : "0x31f1fd284",
      "native_offset" : "0x00000"
   }
,
  {
      "is_managed" : "false",
      "native_address" : "0x31f1fd130",
      "native_offset" : "0x00000"
   }
,
  {
      "is_managed" : "false",
      "native_address" : "0x31f27ccf8",
      "native_offset" : "0x00000"
   }
,
  {
      "is_managed" : "false",
      "native_address" : "0x31f27cc80",
      "native_offset" : "0x00000"
   }
,
  {
      "is_managed" : "false",
      "native_address" : "0x18715ef94",
      "native_offset" : "0x00000"
   }
,
  {
      "is_managed" : "false",
      "native_address" : "0x187159d34",
      "native_offset" : "0x00000"
   }

  ]
 },
 {
    "is_managed" : true,
    "offset_free_hash" : "0x1224727402",
    "offset_rich_hash" : "0x12247275cb",
    "crashed" : false,
    "native_thread_id" : "0x36083f000",
    "thread_info_addr" : "0x125d86600",
    "thread_name" : "Timer-Scheduler",
    "ctx" : {
      "IP" : "0x1871219ec",
      "SP" : "0x36083dec0",
      "BP" : "0x36083df50"
  },
    "managed_frames" : [
  {
      "is_managed" : "false",
      "native_address" : "unregistered"
   }
,
  {
      "is_managed" : "true",
      "guid" : "DA017B87-9D2F-4958-9E8A-5D373B2B6DA4",
      "token" : "0x00000",
      "native_offset" : "0x0",
      "filename" : "mscorlib.dll",
      "sizeofimage" : "0x470000",
      "timestamp" : "0xd7819180",
      "il_offset" : "0xffffffff"
   }
,
  {
      "is_managed" : "true",
      "guid" : "DA017B87-9D2F-4958-9E8A-5D373B2B6DA4",
      "token" : "0x60020b2",
      "native_offset" : "0x0",
      "filename" : "mscorlib.dll",
      "sizeofimage" : "0x470000",
      "timestamp" : "0xd7819180",
      "il_offset" : "0x00044"
   }
,
  {
      "is_managed" : "true",
      "guid" : "DA017B87-9D2F-4958-9E8A-5D373B2B6DA4",
      "token" : "0x600209e",
      "native_offset" : "0x0",
      "filename" : "mscorlib.dll",
      "sizeofimage" : "0x470000",
      "timestamp" : "0xd7819180",
      "il_offset" : "0x00014"
   }
,
  {
      "is_managed" : "true",
      "guid" : "DA017B87-9D2F-4958-9E8A-5D373B2B6DA4",
      "token" : "0x600209d",
      "native_offset" : "0x0",
      "filename" : "mscorlib.dll",
      "sizeofimage" : "0x470000",
      "timestamp" : "0xd7819180",
      "il_offset" : "0x00000"
   }
,
  {
      "is_managed" : "true",
      "guid" : "DA017B87-9D2F-4958-9E8A-5D373B2B6DA4",
      "token" : "0x6002098",
      "native_offset" : "0x0",
      "filename" : "mscorlib.dll",
      "sizeofimage" : "0x470000",
      "timestamp" : "0xd7819180",
      "il_offset" : "0x00019"
   }
,
  {
      "is_managed" : "true",
      "guid" : "DA017B87-9D2F-4958-9E8A-5D373B2B6DA4",
      "token" : "0x600209b",
      "native_offset" : "0x0",
      "filename" : "mscorlib.dll",
      "sizeofimage" : "0x470000",
      "timestamp" : "0xd7819180",
      "il_offset" : "0x00000"
   }
,
  {
      "is_managed" : "true",
      "guid" : "DA017B87-9D2F-4958-9E8A-5D373B2B6DA4",
      "token" : "0x600215a",
      "native_offset" : "0x0",
      "filename" : "mscorlib.dll",
      "sizeofimage" : "0x470000",
      "timestamp" : "0xd7819180",
      "il_offset" : "0x0003c"
   }
,
  {
      "is_managed" : "true",
      "guid" : "DA017B87-9D2F-4958-9E8A-5D373B2B6DA4",
      "token" : "0x6001f7d",
      "native_offset" : "0x0",
      "filename" : "mscorlib.dll",
      "sizeofimage" : "0x470000",
      "timestamp" : "0xd7819180",
      "il_offset" : "0x00014"
   }
,
  {
      "is_managed" : "true",
      "guid" : "DA017B87-9D2F-4958-9E8A-5D373B2B6DA4",
      "token" : "0x6001f25",
      "native_offset" : "0x0",
      "filename" : "mscorlib.dll",
      "sizeofimage" : "0x470000",
      "timestamp" : "0xd7819180",
      "il_offset" : "0x00071"
   }
,
  {
      "is_managed" : "true",
      "guid" : "DA017B87-9D2F-4958-9E8A-5D373B2B6DA4",
      "token" : "0x6001f23",
      "native_offset" : "0x0",
      "filename" : "mscorlib.dll",
      "sizeofimage" : "0x470000",
      "timestamp" : "0xd7819180",
      "il_offset" : "0x00000"
   }
,
  {
      "is_managed" : "true",
      "guid" : "DA017B87-9D2F-4958-9E8A-5D373B2B6DA4",
      "token" : "0x6001f22",
      "native_offset" : "0x0",
      "filename" : "mscorlib.dll",
      "sizeofimage" : "0x470000",
      "timestamp" : "0xd7819180",
      "il_offset" : "0x0002b"
   }
,
  {
      "is_managed" : "true",
      "guid" : "DA017B87-9D2F-4958-9E8A-5D373B2B6DA4",
      "token" : "0x6001f7f",
      "native_offset" : "0x0",
      "filename" : "mscorlib.dll",
      "sizeofimage" : "0x470000",
      "timestamp" : "0xd7819180",
      "il_offset" : "0x00008"
   }
,
  {
      "is_managed" : "true",
      "guid" : "DA017B87-9D2F-4958-9E8A-5D373B2B6DA4",
      "token" : "0x00000",
      "native_offset" : "0x0",
      "filename" : "mscorlib.dll",
      "sizeofimage" : "0x470000",
      "timestamp" : "0xd7819180",
      "il_offset" : "0x00065"
   }

  ],
  "unmanaged_frames" : [
 {
    "is_managed" : "false",
    "native_address" : "0x31f0c519c",
    "native_offset" : "0x00000"
  }
,
 {
    "is_managed" : "false",
    "native_address" : "0x31f1fc518",
    "native_offset" : "0x00000"
  }
,
 {
    "is_managed" : "false",
    "native_address" : "0x31f1fc874",
    "native_offset" : "0x00000"
  }
,
 {
    "is_managed" : "false",
    "native_address" : "0x31f1fc63c",
    "native_offset" : "0x00000"
  }
,
 {
    "is_managed" : "false",
    "native_address" : "0x31f1063cc",
    "native_offset" : "0x00000"
  }
,
 {
    "is_managed" : "false",
    "native_address" : "0x18718f584",
    "native_offset" : "0x00000"
  }
,
 {
    "is_managed" : "false",
    "native_address" : "0x18715f55c",
    "native_offset" : "0x00000"
  }
,
 {
    "is_managed" : "false",
    "native_address" : "0x31f24bd94",
    "native_offset" : "0x00000"
  }
,
 {
    "is_managed" : "false",
    "native_address" : "0x31f208248",
    "native_offset" : "0x00000"
  }
,
 {
    "is_managed" : "false",
    "native_address" : "0x31f20807c",
    "native_offset" : "0x00000"
  }
,
 {
    "is_managed" : "false",
    "native_address" : "0x31f208314",
    "native_offset" : "0x00000"
  }
,
 {
    "is_managed" : "false",
    "native_address" : "0x31f1f76e8",
    "native_offset" : "0x00000"
  }
,
 {
    "is_managed" : "false",
    "native_address" : "0x31f1a1e2c",
    "native_offset" : "0x00000"
  }
,
 {
    "is_managed" : "true",
    "guid" : "DA017B87-9D2F-4958-9E8A-5D373B2B6DA4",
    "token" : "0x00000",
    "native_offset" : "0x0",
    "filename" : "mscorlib.dll",
    "sizeofimage" : "0x470000",
    "timestamp" : "0xd7819180",
    "il_offset" : "0x00000"
  }
,
 {
    "is_managed" : "true",
    "guid" : "DA017B87-9D2F-4958-9E8A-5D373B2B6DA4",
    "token" : "0x60020b2",
    "native_offset" : "0x0",
    "filename" : "mscorlib.dll",
    "sizeofimage" : "0x470000",
    "timestamp" : "0xd7819180",
    "il_offset" : "0x00000"
  }
,
 {
    "is_managed" : "true",
    "guid" : "DA017B87-9D2F-4958-9E8A-5D373B2B6DA4",
    "token" : "0x600209e",
    "native_offset" : "0x0",
    "filename" : "mscorlib.dll",
    "sizeofimage" : "0x470000",
    "timestamp" : "0xd7819180",
    "il_offset" : "0x00000"
  }
,
 {
    "is_managed" : "true",
    "guid" : "DA017B87-9D2F-4958-9E8A-5D373B2B6DA4",
    "token" : "0x600209d",
    "native_offset" : "0x0",
    "filename" : "mscorlib.dll",
    "sizeofimage" : "0x470000",
    "timestamp" : "0xd7819180",
    "il_offset" : "0x00000"
  }
,
 {
    "is_managed" : "true",
    "guid" : "DA017B87-9D2F-4958-9E8A-5D373B2B6DA4",
    "token" : "0x6002098",
    "native_offset" : "0x0",
    "filename" : "mscorlib.dll",
    "sizeofimage" : "0x470000",
    "timestamp" : "0xd7819180",
    "il_offset" : "0x00000"
  }
,
 {
    "is_managed" : "true",
    "guid" : "DA017B87-9D2F-4958-9E8A-5D373B2B6DA4",
    "token" : "0x600209b",
    "native_offset" : "0x0",
    "filename" : "mscorlib.dll",
    "sizeofimage" : "0x470000",
    "timestamp" : "0xd7819180",
    "il_offset" : "0x00000"
  }
,
 {
    "is_managed" : "true",
    "guid" : "DA017B87-9D2F-4958-9E8A-5D373B2B6DA4",
    "token" : "0x600215a",
    "native_offset" : "0x0",
    "filename" : "mscorlib.dll",
    "sizeofimage" : "0x470000",
    "timestamp" : "0xd7819180",
    "il_offset" : "0x00000"
  }
,
 {
    "is_managed" : "true",
    "guid" : "DA017B87-9D2F-4958-9E8A-5D373B2B6DA4",
    "token" : "0x6001f7d",
    "native_offset" : "0x0",
    "filename" : "mscorlib.dll",
    "sizeofimage" : "0x470000",
    "timestamp" : "0xd7819180",
    "il_offset" : "0x00000"
  }
,
 {
    "is_managed" : "true",
    "guid" : "DA017B87-9D2F-4958-9E8A-5D373B2B6DA4",
    "token" : "0x6001f25",
    "native_offset" : "0x0",
    "filename" : "mscorlib.dll",
    "sizeofimage" : "0x470000",
    "timestamp" : "0xd7819180",
    "il_offset" : "0x00000"
  }
,
 {
    "is_managed" : "true",
    "guid" : "DA017B87-9D2F-4958-9E8A-5D373B2B6DA4",
    "token" : "0x6001f23",
    "native_offset" : "0x0",
    "filename" : "mscorlib.dll",
    "sizeofimage" : "0x470000",
    "timestamp" : "0xd7819180",
    "il_offset" : "0x00000"
  }
,
 {
    "is_managed" : "true",
    "guid" : "DA017B87-9D2F-4958-9E8A-5D373B2B6DA4",
    "token" : "0x6001f22",
    "native_offset" : "0x0",
    "filename" : "mscorlib.dll",
    "sizeofimage" : "0x470000",
    "timestamp" : "0xd7819180",
    "il_offset" : "0x00000"
  }
,
 {
    "is_managed" : "true",
    "guid" : "DA017B87-9D2F-4958-9E8A-5D373B2B6DA4",
    "token" : "0x6001f7f",
    "native_offset" : "0x0",
    "filename" : "mscorlib.dll",
    "sizeofimage" : "0x470000",
    "timestamp" : "0xd7819180",
    "il_offset" : "0x00000"
  }
,
 {
    "is_managed" : "true",
    "guid" : "DA017B87-9D2F-4958-9E8A-5D373B2B6DA4",
    "token" : "0x00000",
    "native_offset" : "0x0",
    "filename" : "mscorlib.dll",
    "sizeofimage" : "0x470000",
    "timestamp" : "0xd7819180",
    "il_offset" : "0x00000"
  }
,
 {
    "is_managed" : "false",
    "native_address" : "0x31f054d84",
    "native_offset" : "0x00000"
  }
,
 {
    "is_managed" : "false",
    "native_address" : "0x31f1db24c",
    "native_offset" : "0x00000"
  }
,
 {
    "is_managed" : "false",
    "native_address" : "0x31f1dce5c",
    "native_offset" : "0x00000"
  }
,
 {
    "is_managed" : "false",
    "native_address" : "0x31f1fd378",
    "native_offset" : "0x00000"
  }
,
 {
    "is_managed" : "false",
    "native_address" : "0x31f1fd130",
    "native_offset" : "0x00000"
  }
,
 {
    "is_managed" : "false",
    "native_address" : "0x31f27ccf8",
    "native_offset" : "0x00000"
  }
,
 {
    "is_managed" : "false",
    "native_address" : "0x31f27cc80",
    "native_offset" : "0x00000"
  }
,
 {
    "is_managed" : "false",
    "native_address" : "0x18715ef94",
    "native_offset" : "0x00000"
  }
,
 {
    "is_managed" : "false",
    "native_address" : "0x187159d34",
    "native_offset" : "0x00000"
  }

 ]
},
{
  "is_managed" : false,
  "offset_free_hash" : "0x0",
  "offset_rich_hash" : "0x0",
  "crashed" : false,
  "native_thread_id" : "0x17dbdf000",
  "thread_info_addr" : "0x124f8b600",
  "thread_name" : "tid_d60b",
  "ctx" : {
    "IP" : "0x18711e170",
    "SP" : "0x17dbdece0",
    "BP" : "0x17dbdecf0"
 },
  "unmanaged_frames" : [
 {
    "is_managed" : "false",
    "native_address" : "0x31f0c519c",
    "native_offset" : "0x00000"
  }
,
 {
    "is_managed" : "false",
    "native_address" : "0x31f1fc518",
    "native_offset" : "0x00000"
  }
,
 {
    "is_managed" : "false",
    "native_address" : "0x31f1fc874",
    "native_offset" : "0x00000"
  }
,
 {
    "is_managed" : "false",
    "native_address" : "0x31f1fc63c",
    "native_offset" : "0x00000"
  }
,
 {
    "is_managed" : "false",
    "native_address" : "0x31f1063cc",
    "native_offset" : "0x00000"
  }
,
 {
    "is_managed" : "false",
    "native_address" : "0x18718f584",
    "native_offset" : "0x00000"
  }
,
 {
    "is_managed" : "false",
    "native_address" : "0x186fae984",
    "native_offset" : "0x00000"
  }
,
 {
    "is_managed" : "false",
    "native_address" : "0x186faf034",
    "native_offset" : "0x00000"
  }
,
 {
    "is_managed" : "false",
    "native_address" : "0x1059b4164",
    "native_offset" : "0x00000"
  }
,
 {
    "is_managed" : "false",
    "native_address" : "0x1036b91d4",
    "native_offset" : "0x00000"
  }
,
 {
    "is_managed" : "false",
    "native_address" : "0x1036ba22c",
    "native_offset" : "0x00000"
  }
,
 {
    "is_managed" : "false",
    "native_address" : "0x10392287c",
    "native_offset" : "0x00000"
  }
,
 {
    "is_managed" : "false",
    "native_address" : "0x18715ef94",
    "native_offset" : "0x00000"
  }
,
 {
    "is_managed" : "false",
    "native_address" : "0x187159d34",
    "native_offset" : "0x00000"
  }

 ]
},
{
  "is_managed" : false,
  "offset_free_hash" : "0x0",
  "offset_rich_hash" : "0x0",
  "crashed" : false,
  "native_thread_id" : "0x17dc6b000",
  "thread_info_addr" : "0x34ac71600",
  "thread_name" : "tid_10103",
  "ctx" : {
    "IP" : "0x18711e170",
    "SP" : "0x17dc6ace0",
    "BP" : "0x17dc6acf0"
 },
  "unmanaged_frames" : [
 {
    "is_managed" : "false",
    "native_address" : "0x31f0c519c",
    "native_offset" : "0x00000"
  }
,
 {
    "is_managed" : "false",
    "native_address" : "0x31f1fc518",
    "native_offset" : "0x00000"
  }
,
 {
    "is_managed" : "false",
    "native_address" : "0x31f1fc874",
    "native_offset" : "0x00000"
  }
,
 {
    "is_managed" : "false",
    "native_address" : "0x31f1fc63c",
    "native_offset" : "0x00000"
  }
,
 {
    "is_managed" : "false",
    "native_address" : "0x31f1063cc",
    "native_offset" : "0x00000"
  }
,
 {
    "is_managed" : "false",
    "native_address" : "0x18718f584",
    "native_offset" : "0x00000"
  }
,
 {
    "is_managed" : "false",
    "native_address" : "0x186fae984",
    "native_offset" : "0x00000"
  }
,
 {
    "is_managed" : "false",
    "native_address" : "0x186faf034",
    "native_offset" : "0x00000"
  }
,
 {
    "is_managed" : "false",
    "native_address" : "0x1059b4164",
    "native_offset" : "0x00000"
  }
,
 {
    "is_managed" : "false",
    "native_address" : "0x1036b91d4",
    "native_offset" : "0x00000"
  }
,
 {
    "is_managed" : "false",
    "native_address" : "0x1036ba22c",
    "native_offset" : "0x00000"
  }
,
 {
    "is_managed" : "false",
    "native_address" : "0x10392287c",
    "native_offset" : "0x00000"
  }
,
 {
    "is_managed" : "false",
    "native_address" : "0x18715ef94",
    "native_offset" : "0x00000"
  }
,
 {
    "is_managed" : "false",
    "native_address" : "0x187159d34",
    "native_offset" : "0x00000"
  }

 ]
},
{
  "is_managed" : false,
  "offset_free_hash" : "0x0",
  "offset_rich_hash" : "0x0",
  "crashed" : false,
  "native_thread_id" : "0x17dcf7000",
  "thread_info_addr" : "0x120012c00",
  "thread_name" : "tid_15403",
  "ctx" : {
    "IP" : "0x18711e170",
    "SP" : "0x17dcf6ce0",
    "BP" : "0x17dcf6cf0"
 },
  "unmanaged_frames" : [
 {
    "is_managed" : "false",
    "native_address" : "0x31f0c519c",
    "native_offset" : "0x00000"
  }
,
 {
    "is_managed" : "false",
    "native_address" : "0x31f1fc518",
    "native_offset" : "0x00000"
  }
,
 {
    "is_managed" : "false",
    "native_address" : "0x31f1fc874",
    "native_offset" : "0x00000"
  }
,
 {
    "is_managed" : "false",
    "native_address" : "0x31f1fc63c",
    "native_offset" : "0x00000"
  }
,
 {
    "is_managed" : "false",
    "native_address" : "0x31f1063cc",
    "native_offset" : "0x00000"
  }
,
 {
    "is_managed" : "false",
    "native_address" : "0x18718f584",
    "native_offset" : "0x00000"
  }
,
 {
    "is_managed" : "false",
    "native_address" : "0x186fae984",
    "native_offset" : "0x00000"
  }
,
 {
    "is_managed" : "false",
    "native_address" : "0x186faf034",
    "native_offset" : "0x00000"
  }
,
 {
    "is_managed" : "false",
    "native_address" : "0x1059b4164",
    "native_offset" : "0x00000"
  }
,
 {
    "is_managed" : "false",
    "native_address" : "0x1036b91d4",
    "native_offset" : "0x00000"
  }
,
 {
    "is_managed" : "false",
    "native_address" : "0x1036ba22c",
    "native_offset" : "0x00000"
  }
,
 {
    "is_managed" : "false",
    "native_address" : "0x10392287c",
    "native_offset" : "0x00000"
  }
,
 {
    "is_managed" : "false",
    "native_address" : "0x18715ef94",
    "native_offset" : "0x00000"
  }
,
 {
    "is_managed" : "false",
    "native_address" : "0x187159d34",
    "native_offset" : "0x00000"
  }

 ]
},
{
  "is_managed" : false,
  "offset_free_hash" : "0x0",
  "offset_rich_hash" : "0x0",
  "crashed" : false,
  "native_thread_id" : "0x35f707000",
  "thread_info_addr" : "0x32493e000",
  "thread_name" : "Thread Pool Worker",
  "ctx" : {
    "IP" : "0x18711e188",
    "SP" : "0x35f706db0",
    "BP" : "0x35f706e50"
 },
  "unmanaged_frames" : [
 {
    "is_managed" : "false",
    "native_address" : "0x31f0c519c",
    "native_offset" : "0x00000"
  }
,
 {
    "is_managed" : "false",
    "native_address" : "0x31f1fc518",
    "native_offset" : "0x00000"
  }
,
 {
    "is_managed" : "false",
    "native_address" : "0x31f1fc874",
    "native_offset" : "0x00000"
  }
,
 {
    "is_managed" : "false",
    "native_address" : "0x31f1fc63c",
    "native_offset" : "0x00000"
  }
,
 {
    "is_managed" : "false",
    "native_address" : "0x31f1063cc",
    "native_offset" : "0x00000"
  }
,
 {
    "is_managed" : "false",
    "native_address" : "0x18718f584",
    "native_offset" : "0x00000"
  }
,
 {
    "is_managed" : "false",
    "native_address" : "0x31f1551c0",
    "native_offset" : "0x00000"
  }
,
 {
    "is_managed" : "false",
    "native_address" : "0x31f1fd284",
    "native_offset" : "0x00000"
  }
,
 {
    "is_managed" : "false",
    "native_address" : "0x31f1fd130",
    "native_offset" : "0x00000"
  }
,
 {
    "is_managed" : "false",
    "native_address" : "0x31f27ccf8",
    "native_offset" : "0x00000"
  }
,
 {
    "is_managed" : "false",
    "native_address" : "0x31f27cc80",
    "native_offset" : "0x00000"
  }
,
 {
    "is_managed" : "false",
    "native_address" : "0x18715ef94",
    "native_offset" : "0x00000"
  }
,
 {
    "is_managed" : "false",
    "native_address" : "0x187159d34",
    "native_offset" : "0x00000"
  }

 ]
},
{
  "is_managed" : false,
  "offset_free_hash" : "0x0",
  "offset_rich_hash" : "0x0",
  "crashed" : false,
  "native_thread_id" : "0x358a07000",
  "thread_info_addr" : "0x12281ba00",
  "thread_name" : "Thread Pool Worker",
  "ctx" : {
    "IP" : "0x18711e188",
    "SP" : "0x358a06db0",
    "BP" : "0x358a06e50"
 },
  "unmanaged_frames" : [
 {
    "is_managed" : "false",
    "native_address" : "0x31f0c519c",
    "native_offset" : "0x00000"
  }
,
 {
    "is_managed" : "false",
    "native_address" : "0x31f1fc518",
    "native_offset" : "0x00000"
  }
,
 {
    "is_managed" : "false",
    "native_address" : "0x31f1fc874",
    "native_offset" : "0x00000"
  }
,
 {
    "is_managed" : "false",
    "native_address" : "0x31f1fc63c",
    "native_offset" : "0x00000"
  }
,
 {
    "is_managed" : "false",
    "native_address" : "0x31f1063cc",
    "native_offset" : "0x00000"
  }
,
 {
    "is_managed" : "false",
    "native_address" : "0x18718f584",
    "native_offset" : "0x00000"
  }
,
 {
    "is_managed" : "false",
    "native_address" : "0x31f1551c0",
    "native_offset" : "0x00000"
  }
,
 {
    "is_managed" : "false",
    "native_address" : "0x31f1fd284",
    "native_offset" : "0x00000"
  }
,
 {
    "is_managed" : "false",
    "native_address" : "0x31f1fd130",
    "native_offset" : "0x00000"
  }
,
 {
    "is_managed" : "false",
    "native_address" : "0x31f27ccf8",
    "native_offset" : "0x00000"
  }
,
 {
    "is_managed" : "false",
    "native_address" : "0x31f27cc80",
    "native_offset" : "0x00000"
  }
,
 {
    "is_managed" : "false",
    "native_address" : "0x18715ef94",
    "native_offset" : "0x00000"
  }
,
 {
    "is_managed" : "false",
    "native_address" : "0x187159d34",
    "native_offset" : "0x00000"
  }

 ]
},
{
  "is_managed" : false,
  "offset_free_hash" : "0x0",
  "offset_rich_hash" : "0x0",
  "crashed" : false,
  "native_thread_id" : "0x370607000",
  "thread_info_addr" : "0x32983c600",
  "thread_name" : "Thread Pool Worker",
  "ctx" : {
    "IP" : "0x18711e188",
    "SP" : "0x370606db0",
    "BP" : "0x370606e50"
 },
  "unmanaged_frames" : [
 {
    "is_managed" : "false",
    "native_address" : "0x31f0c519c",
    "native_offset" : "0x00000"
  }
,
 {
    "is_managed" : "false",
    "native_address" : "0x31f1fc518",
    "native_offset" : "0x00000"
  }
,
 {
    "is_managed" : "false",
    "native_address" : "0x31f1fc874",
    "native_offset" : "0x00000"
  }
,
 {
    "is_managed" : "false",
    "native_address" : "0x31f1fc63c",
    "native_offset" : "0x00000"
  }
,
 {
    "is_managed" : "false",
    "native_address" : "0x31f1063cc",
    "native_offset" : "0x00000"
  }
,
 {
    "is_managed" : "false",
    "native_address" : "0x18718f584",
    "native_offset" : "0x00000"
  }
,
 {
    "is_managed" : "false",
    "native_address" : "0x31f1551c0",
    "native_offset" : "0x00000"
  }
,
 {
    "is_managed" : "false",
    "native_address" : "0x31f1fd284",
    "native_offset" : "0x00000"
  }
,
 {
    "is_managed" : "false",
    "native_address" : "0x31f1fd130",
    "native_offset" : "0x00000"
  }
,
 {
    "is_managed" : "false",
    "native_address" : "0x31f27ccf8",
    "native_offset" : "0x00000"
  }
,
 {
    "is_managed" : "false",
    "native_address" : "0x31f27cc80",
    "native_offset" : "0x00000"
  }
,
 {
    "is_managed" : "false",
    "native_address" : "0x18715ef94",
    "native_offset" : "0x00000"
  }
,
 {
    "is_managed" : "false",
    "native_address" : "0x187159d34",
    "native_offset" : "0x00000"
  }

 ]
},
{
  "is_managed" : false,
  "offset_free_hash" : "0x0",
  "offset_rich_hash" : "0x0",
  "crashed" : false,
  "native_thread_id" : "0x17dd83000",
  "thread_info_addr" : "0x32991d800",
  "thread_name" : "tid_15303",
  "ctx" : {
    "IP" : "0x18711e170",
    "SP" : "0x17dd82ce0",
    "BP" : "0x17dd82cf0"
 },
  "unmanaged_frames" : [
 {
    "is_managed" : "false",
    "native_address" : "0x31f0c519c",
    "native_offset" : "0x00000"
  }
,
 {
    "is_managed" : "false",
    "native_address" : "0x31f1fc518",
    "native_offset" : "0x00000"
  }
,
 {
    "is_managed" : "false",
    "native_address" : "0x31f1fc874",
    "native_offset" : "0x00000"
  }
,
 {
    "is_managed" : "false",
    "native_address" : "0x31f1fc63c",
    "native_offset" : "0x00000"
  }
,
 {
    "is_managed" : "false",
    "native_address" : "0x31f1063cc",
    "native_offset" : "0x00000"
  }
,
 {
    "is_managed" : "false",
    "native_address" : "0x18718f584",
    "native_offset" : "0x00000"
  }
,
 {
    "is_managed" : "false",
    "native_address" : "0x186fae984",
    "native_offset" : "0x00000"
  }
,
 {
    "is_managed" : "false",
    "native_address" : "0x186faf034",
    "native_offset" : "0x00000"
  }
,
 {
    "is_managed" : "false",
    "native_address" : "0x1059b4164",
    "native_offset" : "0x00000"
  }
,
 {
    "is_managed" : "false",
    "native_address" : "0x1036b91d4",
    "native_offset" : "0x00000"
  }
,
 {
    "is_managed" : "false",
    "native_address" : "0x1036ba22c",
    "native_offset" : "0x00000"
  }
,
 {
    "is_managed" : "false",
    "native_address" : "0x10392287c",
    "native_offset" : "0x00000"
  }
,
 {
    "is_managed" : "false",
    "native_address" : "0x18715ef94",
    "native_offset" : "0x00000"
  }
,
 {
    "is_managed" : "false",
    "native_address" : "0x187159d34",
    "native_offset" : "0x00000"
  }

 ]
},
{
  "is_managed" : false,
  "offset_free_hash" : "0x0",
  "offset_rich_hash" : "0x0",
  "crashed" : false,
  "native_thread_id" : "0x35f08b000",
  "thread_info_addr" : "0x126859600",
  "thread_name" : "Thread Pool Worker",
  "ctx" : {
    "IP" : "0x18711e188",
    "SP" : "0x35f08adb0",
    "BP" : "0x35f08ae50"
 },
  "unmanaged_frames" : [
 {
    "is_managed" : "false",
    "native_address" : "0x31f0c519c",
    "native_offset" : "0x00000"
  }
,
 {
    "is_managed" : "false",
    "native_address" : "0x31f1fc518",
    "native_offset" : "0x00000"
  }
,
 {
    "is_managed" : "false",
    "native_address" : "0x31f1fc874",
    "native_offset" : "0x00000"
  }
,
 {
    "is_managed" : "false",
    "native_address" : "0x31f1fc63c",
    "native_offset" : "0x00000"
  }
,
 {
    "is_managed" : "false",
    "native_address" : "0x31f1063cc",
    "native_offset" : "0x00000"
  }
,
 {
    "is_managed" : "false",
    "native_address" : "0x18718f584",
    "native_offset" : "0x00000"
  }
,
 {
    "is_managed" : "false",
    "native_address" : "0x31f1551c0",
    "native_offset" : "0x00000"
  }
,
 {
    "is_managed" : "false",
    "native_address" : "0x31f1fd284",
    "native_offset" : "0x00000"
  }
,
 {
    "is_managed" : "false",
    "native_address" : "0x31f1fd130",
    "native_offset" : "0x00000"
  }
,
 {
    "is_managed" : "false",
    "native_address" : "0x31f27ccf8",
    "native_offset" : "0x00000"
  }
,
 {
    "is_managed" : "false",
    "native_address" : "0x31f27cc80",
    "native_offset" : "0x00000"
  }
,
 {
    "is_managed" : "false",
    "native_address" : "0x18715ef94",
    "native_offset" : "0x00000"
  }
,
 {
    "is_managed" : "false",
    "native_address" : "0x187159d34",
    "native_offset" : "0x00000"
  }

 ]
},
{
  "is_managed" : false,
  "offset_free_hash" : "0x0",
  "offset_rich_hash" : "0x0",
  "crashed" : false,
  "native_thread_id" : "0x3656ef000",
  "thread_info_addr" : "0x12284e200",
  "thread_name" : "Thread Pool Worker",
  "ctx" : {
    "IP" : "0x18711e188",
    "SP" : "0x3656eedb0",
    "BP" : "0x3656eee50"
 },
  "unmanaged_frames" : [
 {
    "is_managed" : "false",
    "native_address" : "0x31f0c519c",
    "native_offset" : "0x00000"
  }
,
 {
    "is_managed" : "false",
    "native_address" : "0x31f1fc518",
    "native_offset" : "0x00000"
  }
,
 {
    "is_managed" : "false",
    "native_address" : "0x31f1fc874",
    "native_offset" : "0x00000"
  }
,
 {
    "is_managed" : "false",
    "native_address" : "0x31f1fc63c",
    "native_offset" : "0x00000"
  }
,
 {
    "is_managed" : "false",
    "native_address" : "0x31f1063cc",
    "native_offset" : "0x00000"
  }
,
 {
    "is_managed" : "false",
    "native_address" : "0x18718f584",
    "native_offset" : "0x00000"
  }
,
 {
    "is_managed" : "false",
    "native_address" : "0x31f1551c0",
    "native_offset" : "0x00000"
  }
,
 {
    "is_managed" : "false",
    "native_address" : "0x31f1fd284",
    "native_offset" : "0x00000"
  }
,
 {
    "is_managed" : "false",
    "native_address" : "0x31f1fd130",
    "native_offset" : "0x00000"
  }
,
 {
    "is_managed" : "false",
    "native_address" : "0x31f27ccf8",
    "native_offset" : "0x00000"
  }
,
 {
    "is_managed" : "false",
    "native_address" : "0x31f27cc80",
    "native_offset" : "0x00000"
  }
,
 {
    "is_managed" : "false",
    "native_address" : "0x18715ef94",
    "native_offset" : "0x00000"
  }
,
 {
    "is_managed" : "false",
    "native_address" : "0x187159d34",
    "native_offset" : "0x00000"
  }

 ]
}
]
}